model_schema/__init__.py
model_schema/card.py
model_schema/loader.py
model_schema/model_schema.json
model_schema/output.py
model_schema/validator.py
model_schema-1.3.1.dist-info/licenses/LICENSE.md
model_schema-1.3.1.dist-info/METADATA
model_schema-1.3.1.dist-info/WHEEL
model_schema-1.3.1.dist-info/top_level.txt
model_schema-1.3.1.dist-info/RECORD
