Metadata-Version: 2.4
Name: model-schema
Version: 1.3.1
Summary: Standardised manifest creation and validation for machine-learning models
Author-email: Zachary Szewczyk <zacjszewczyk@gmail.com>
License: License
Project-URL: Homepage, https://github.com/zacjszewczyk/model-schema
Project-URL: Issues, https://github.com/zacjszewczyk/model-schema/issues
Classifier: Programming Language :: Python :: 3
Classifier: License :: OSI Approved :: Apache Software License
Classifier: Operating System :: OS Independent
Requires-Python: >=3.8
License-File: LICENSE.md
Dynamic: license-file
